telegram_to_rss/__init__.py
telegram_to_rss/__main__.py
telegram_to_rss/client.py
telegram_to_rss/config.py
telegram_to_rss/consts.py
telegram_to_rss/db.py
telegram_to_rss/generate_feed.py
telegram_to_rss/models/__init__.py
telegram_to_rss/models/feed.py
telegram_to_rss/models/feed_entry.py
telegram_to_rss/poll_telegram.py
telegram_to_rss/qr_code.py
telegram_to_rss/server.py
telegram_to_rss/templates/base.html
telegram_to_rss/templates/feeds.html
telegram_to_rss/templates/qr_code.html
telegram_to_rss-0.3.0.dist-info/LICENSE
telegram_to_rss-0.3.0.dist-info/METADATA
telegram_to_rss-0.3.0.dist-info/WHEEL
telegram_to_rss-0.3.0.dist-info/entry_points.txt
telegram_to_rss-0.3.0.dist-info/RECORD
