Metadata-Version: 2.1
Name: telegram-to-rss
Version: 0.3.0
Summary: 
License: MIT
Author: aigoncharov
Requires-Python: >=3.12,<4.0
Classifier: License :: OSI Approved :: MIT License
Classifier: Programming Language :: Python :: 3
Classifier: Programming Language :: Python :: 3.12
Requires-Dist: Telethon (>=1.36.0,<2.0.0)
Requires-Dist: anyio (>=4.4.0,<5.0.0)
Requires-Dist: cryptg (>=0.4.0,<0.5.0)
Requires-Dist: hypercorn (>=0.17.3,<0.18.0)
Requires-Dist: platformdirs (>=4.2.2,<5.0.0)
Requires-Dist: qrcode (>=7.4.2,<8.0.0)
Requires-Dist: quart (>=0.19.6,<0.20.0)
Requires-Dist: tortoise-orm (>=0.21.3,<0.22.0)
